<?xml version="1.0" encoding="UTF-8" standalone="no"?>
<event category="CREATE" id="0">
  <actions>
    <action id="603" library="1">
      <!--action name: Code-->
      <kind>CODE</kind>
      <allowRelative>false</allowRelative>
      <question>false</question>
      <canApplyTo>true</canApplyTo>
      <actionType>CODE</actionType>
      <functionName/>
      <relative>false</relative>
      <not>false</not>
      <appliesTo>.self</appliesTo>
      <arguments>
        <argument kind="STRING">event_inherited()

interpSpeed = 25


moveTimer = 0
moveTimerMax = 30
moveTimerMin = 10

dStatementAdd(0, "Yeah maybe", 2037, 2248)
dResponseAdd(0, "test", 1)
dResponseAdd(0, "responses and shit", 2)

dStatementAdd(1, "", 2375, 2266)

dStatementAdd(2, "It's got a* pathfinding", 2422, 2305)
dResponseAdd(2, "agdnnnnnnnnnnnnnnnnnnnnn fdanfadfnadsnfadsptea ea e", 3)

dStatementAdd(3, "[exit]", 2784, 2326)


</argument>
      </arguments>
    </action>
  </actions>
</event>
